README.md
setup.py
django_extant_test_db.egg-info/PKG-INFO
django_extant_test_db.egg-info/SOURCES.txt
django_extant_test_db.egg-info/dependency_links.txt
django_extant_test_db.egg-info/top_level.txt
extant_test_db/__init__.py
extant_test_db/runner.py