Metadata-Version: 1.0
Name: django-extant-test-db
Version: 0.1.4
Summary: UNKNOWN
Home-page: https://github.com/mjumbewu/django-extant-test-db
Author: Mjumbe Poe
Author-email: mjumbewu@gmail.com
License: UNKNOWN
Platform: UNKNOWN
